setuptools_cuda/__init__.py
setuptools_cuda/build.py
setuptools_cuda/compiler_customization.py
setuptools_cuda/extension.py
setuptools_cuda/inspections.py
setuptools_cuda/setuptools_ext.py
setuptools_cuda-0.0.6.dist-info/METADATA
setuptools_cuda-0.0.6.dist-info/WHEEL
setuptools_cuda-0.0.6.dist-info/entry_points.txt
setuptools_cuda-0.0.6.dist-info/top_level.txt
setuptools_cuda-0.0.6.dist-info/RECORD
