Metadata-Version: 2.1
Name: setuptools-cuda
Version: 0.0.6
Summary: Setuptools plugin for compiling CUDA-enable extension modules
Classifier: Operating System :: POSIX :: Linux
Provides-Extra: dev
Requires-Dist: flake8 (>=4.0.1) ; extra == 'dev'
Requires-Dist: black (>=21.12b0) ; extra == 'dev'
Requires-Dist: isort (>=5.10.1) ; extra == 'dev'
Requires-Dist: mypy (>=0.961) ; extra == 'dev'
Provides-Extra: docs
Requires-Dist: sphinx (~=5.3.0) ; extra == 'docs'
Requires-Dist: pydata-sphinx-theme (~=0.11.0) ; extra == 'docs'
Requires-Dist: sphinx-math-dollar (~=1.2.1) ; extra == 'docs'
Requires-Dist: myst-parser (~=0.18.1) ; extra == 'docs'
Requires-Dist: iplantuml (~=0.1.1) ; extra == 'docs'
Requires-Dist: sphinx-design (~=0.3.0) ; extra == 'docs'
